{
  "tabs": [
    {
      "caption": "Общая информация",
      "fullFields": [
        {
          "caption": "Лист",
          "type": 1,
          "property": "sheet",
          "size": 2,
          "maskName": null,
          "mask": null,
          "mode": null,
          "fields": [],
          "columns": [],
          "actions": null,
          "commands": null,
          "orderNumber": 60,
          "required": true,
          "visibility": null,
          "enablement": null,
          "obligation": null,
          "readonly": false,
          "selectionPaginated": true,
          "validators": null,
          "hint": "",
          "historyDisplayMode": 0,
          "tags": null,
          "selConditions": [],
          "selSorting": []
        },
        {
          "caption": "Архивная ссылка на документ",
          "type": 5,
          "property": "archLinkDoc",
          "size": 2,
          "maskName": null,
          "mask": null,
          "mode": 1,
          "fields": [],
          "columns": [],
          "actions": null,
          "commands": [],
          "orderNumber": 50,
          "required": true,
          "visibility": null,
          "enablement": null,
          "obligation": null,
          "readonly": false,
          "selectionPaginated": true,
          "validators": null,
          "hint": "",
          "historyDisplayMode": 0,
          "tags": null,
          "selConditions": [],
          "selSorting": []
        },
        {
          "caption": "Район, из которого получен архивный документ",
          "type": 5,
          "property": "districtArchDoc",
          "size": 2,
          "maskName": null,
          "mask": null,
          "mode": null,
          "fields": [],
          "columns": [],
          "actions": null,
          "commands": [],
          "orderNumber": 40,
          "required": true,
          "visibility": null,
          "enablement": null,
          "obligation": null,
          "readonly": false,
          "selectionPaginated": true,
          "validators": null,
          "hint": "",
          "historyDisplayMode": 0,
          "tags": null,
          "selConditions": [],
          "selSorting": []
        }
      ],
      "shortFields": []
    },
    {
      "caption": "Информация из документа",
      "fullFields": [
        {
          "caption": "Фамилия",
          "type": 1,
          "property": "surname",
          "size": 2,
          "maskName": null,
          "mask": null,
          "mode": null,
          "fields": [],
          "columns": [],
          "actions": null,
          "commands": null,
          "orderNumber": 10,
          "required": true,
          "visibility": null,
          "enablement": null,
          "obligation": null,
          "readonly": false,
          "selectionPaginated": true,
          "validators": null,
          "hint": "",
          "historyDisplayMode": 0,
          "tags": null,
          "selConditions": [],
          "selSorting": []
        },
        {
          "caption": "Имя",
          "type": 1,
          "property": "firstname",
          "size": 2,
          "maskName": null,
          "mask": null,
          "mode": null,
          "fields": [],
          "columns": [],
          "actions": null,
          "commands": null,
          "orderNumber": 20,
          "required": false,
          "visibility": null,
          "enablement": null,
          "obligation": null,
          "readonly": false,
          "selectionPaginated": true,
          "validators": null,
          "hint": "",
          "historyDisplayMode": 0,
          "tags": null,
          "selConditions": [],
          "selSorting": []
        },
        {
          "caption": "Отчество",
          "type": 1,
          "property": "secondname",
          "size": 2,
          "maskName": null,
          "mask": null,
          "mode": null,
          "fields": [],
          "columns": [],
          "actions": null,
          "commands": null,
          "orderNumber": 30,
          "required": false,
          "visibility": null,
          "enablement": null,
          "obligation": null,
          "readonly": false,
          "selectionPaginated": true,
          "validators": null,
          "hint": "",
          "historyDisplayMode": 0,
          "tags": null,
          "selConditions": [],
          "selSorting": []
        },
        {
          "caption": "Дата рождения/Возраст",
          "type": 1,
          "property": "dateBirth",
          "size": 2,
          "maskName": null,
          "mask": null,
          "mode": null,
          "fields": [],
          "columns": [],
          "actions": null,
          "commands": null,
          "orderNumber": 40,
          "required": false,
          "visibility": null,
          "enablement": null,
          "obligation": null,
          "readonly": false,
          "selectionPaginated": true,
          "validators": null,
          "hint": "",
          "historyDisplayMode": 0,
          "tags": null,
          "selConditions": [],
          "selSorting": []
        },
        {
          "caption": "Образование",
          "type": 1,
          "property": "education",
          "size": 2,
          "maskName": null,
          "mask": null,
          "mode": null,
          "fields": [],
          "columns": [],
          "actions": null,
          "commands": null,
          "orderNumber": 50,
          "required": false,
          "visibility": null,
          "enablement": null,
          "obligation": null,
          "readonly": false,
          "selectionPaginated": true,
          "validators": null,
          "hint": "",
          "historyDisplayMode": 0,
          "tags": null,
          "selConditions": [],
          "selSorting": []
        },
        {
          "caption": "Партийность",
          "type": 1,
          "property": "partyMembership",
          "size": 2,
          "maskName": null,
          "mask": null,
          "mode": null,
          "fields": [],
          "columns": [],
          "actions": null,
          "commands": null,
          "orderNumber": 60,
          "required": false,
          "visibility": null,
          "enablement": null,
          "obligation": null,
          "readonly": false,
          "selectionPaginated": true,
          "validators": null,
          "hint": "",
          "historyDisplayMode": 0,
          "tags": null,
          "selConditions": [],
          "selSorting": []
        },
        {
          "caption": "Когда отправлен в часть",
          "type": 1,
          "property": "whenSentPart",
          "size": 2,
          "maskName": null,
          "mask": null,
          "mode": null,
          "fields": [],
          "columns": [],
          "actions": null,
          "commands": null,
          "orderNumber": 80,
          "required": false,
          "visibility": null,
          "enablement": null,
          "obligation": null,
          "readonly": false,
          "selectionPaginated": true,
          "validators": null,
          "hint": "",
          "historyDisplayMode": 0,
          "tags": null,
          "selConditions": [],
          "selSorting": []
        },
        {
          "caption": "В какую команду или часть направлен",
          "type": 1,
          "property": "teamPartSent",
          "size": 2,
          "maskName": null,
          "mask": null,
          "mode": null,
          "fields": [],
          "columns": [],
          "actions": null,
          "commands": null,
          "orderNumber": 90,
          "required": false,
          "visibility": null,
          "enablement": null,
          "obligation": null,
          "readonly": false,
          "selectionPaginated": true,
          "validators": null,
          "hint": "",
          "historyDisplayMode": 0,
          "tags": null,
          "selConditions": [],
          "selSorting": []
        },
        {
          "caption": "Место работы до призыва",
          "type": 1,
          "property": "placeWorkBeforeConscription",
          "size": 2,
          "maskName": null,
          "mask": null,
          "mode": null,
          "fields": [],
          "columns": [],
          "actions": null,
          "commands": null,
          "orderNumber": 100,
          "required": false,
          "visibility": null,
          "enablement": null,
          "obligation": null,
          "readonly": false,
          "selectionPaginated": true,
          "validators": null,
          "hint": "",
          "historyDisplayMode": 0,
          "tags": null,
          "selConditions": [],
          "selSorting": []
        },
        {
          "caption": "Примечание",
          "type": 1,
          "property": "note",
          "size": 2,
          "maskName": null,
          "mask": null,
          "mode": null,
          "fields": [],
          "columns": [],
          "actions": null,
          "commands": null,
          "orderNumber": 110,
          "required": false,
          "visibility": null,
          "enablement": null,
          "obligation": null,
          "readonly": false,
          "selectionPaginated": true,
          "validators": null,
          "hint": "",
          "historyDisplayMode": 0,
          "tags": null,
          "selConditions": [],
          "selSorting": []
        },
        {
          "caption": "Оцифрованное изображение архивного документа",
          "type": 2,
          "property": "scanFileLink",
          "size": 2,
          "maskName": null,
          "mask": null,
          "mode": 1,
          "fields": [],
          "columns": [],
          "actions": null,
          "commands": [
            {
              "id": "SELECT",
              "caption": "Выбрать",
              "visibilityCondition": null,
              "enableCondition": null,
              "needSelectedItem": false,
              "signBefore": false,
              "signAfter": false,
              "isBulk": false
            },
            {
              "id": "REMOVE",
              "caption": "Убрать",
              "visibilityCondition": null,
              "enableCondition": null,
              "needSelectedItem": false,
              "signBefore": false,
              "signAfter": false,
              "isBulk": false
            }
          ],
          "orderNumber": 120,
          "required": false,
          "visibility": null,
          "enablement": null,
          "obligation": null,
          "readonly": false,
          "selectionPaginated": false,
          "validators": null,
          "hint": "",
          "historyDisplayMode": 0,
          "tags": null,
          "selConditions": [],
          "selSorting": []
        },
        {
          "caption": "Внешняя ссылка на оцифрованное изображение архивного документа в файле",
          "type": 17,
          "property": "urlScanFile",
          "size": 2,
          "maskName": null,
          "mask": null,
          "mode": null,
          "fields": [],
          "columns": [],
          "actions": null,
          "commands": null,
          "orderNumber": 140,
          "required": false,
          "visibility": null,
          "enablement": null,
          "obligation": null,
          "readonly": false,
          "selectionPaginated": true,
          "validators": null,
          "hint": "",
          "historyDisplayMode": 0,
          "tags": null,
          "selConditions": [],
          "selSorting": []
        },
        {
          "caption": "Файл",
          "type": 11,
          "property": "storageForFile",
          "size": 2,
          "maskName": null,
          "mask": null,
          "mode": null,
          "fields": [],
          "columns": [],
          "actions": null,
          "commands": null,
          "orderNumber": 130,
          "required": false,
          "visibility": ".isShowStorageFile \u003d\u003d \"true\"",
          "enablement": null,
          "obligation": null,
          "readonly": false,
          "selectionPaginated": true,
          "validators": null,
          "hint": "",
          "historyDisplayMode": 0,
          "tags": null,
          "selConditions": [],
          "selSorting": []
        },
        {
          "caption": "Отобразить ссылку на файл",
          "type": 4,
          "property": "isShowStorageFile",
          "size": 2,
          "maskName": null,
          "mask": null,
          "mode": null,
          "fields": [],
          "columns": [],
          "actions": null,
          "commands": null,
          "orderNumber": 125,
          "required": false,
          "visibility": null,
          "enablement": null,
          "obligation": null,
          "readonly": false,
          "selectionPaginated": true,
          "validators": null,
          "hint": "",
          "historyDisplayMode": 0,
          "tags": null,
          "selConditions": [],
          "selSorting": []
        },
        {
          "caption": "Файл (оборотная стороная)",
          "type": 11,
          "property": "storageForFileBack",
          "size": 2,
          "maskName": null,
          "mask": null,
          "mode": null,
          "fields": [],
          "columns": [],
          "actions": null,
          "commands": null,
          "orderNumber": 133,
          "required": false,
          "visibility": ".isShowStorageFile \u003d\u003d \"true\"",
          "enablement": null,
          "obligation": null,
          "readonly": false,
          "selectionPaginated": true,
          "validators": null,
          "hint": "",
          "historyDisplayMode": 0,
          "tags": null,
          "selConditions": [],
          "selSorting": []
        }
      ],
      "shortFields": []
    }
  ],
  "actions": null,
  "siblingFixBy": null,
  "siblingNavigateBy": null,
  "historyDisplayMode": 0,
  "collectionFilters": null,
  "version": null,
  "overrideMode": 0,
  "commands": [
    {
      "id": "SAVE",
      "caption": "Сохранить",
      "visibilityCondition": null,
      "enableCondition": null,
      "needSelectedItem": false,
      "signBefore": false,
      "signAfter": false,
      "isBulk": false
    },
    {
      "id": "SAVEANDCLOSE",
      "caption": "Сохранить и закрыть",
      "visibilityCondition": null,
      "enableCondition": null,
      "needSelectedItem": false,
      "signBefore": false,
      "signAfter": false,
      "isBulk": false
    }
  ],
  "metaVersion": "2.0.61.23689"
}